hero_crawl-0.1.4.dist-info/DESCRIPTION.rst
hero_crawl-0.1.4.dist-info/METADATA
hero_crawl-0.1.4.dist-info/RECORD
hero_crawl-0.1.4.dist-info/WHEEL
hero_crawl-0.1.4.dist-info/metadata.json
hero_crawl-0.1.4.dist-info/top_level.txt
vanko/__init__.py
vanko/excel/__init__.py
vanko/excel/base.py
vanko/excel/csvwriter.py
vanko/excel/openpyxl.py
vanko/excel/xlsxwriter.py
vanko/flask/__init__.py
vanko/flask/admin.py
vanko/flask/admin_pymongo.py
vanko/flask/admin_redis.py
vanko/flask/admin_sqla.py
vanko/flask/compat.py
vanko/flask/forms.py
vanko/flask/ping.py
vanko/flask/session.py
vanko/flask/sqla.py
vanko/flask/utils.py
vanko/scrapy/__init__.py
vanko/scrapy/crawl.py
vanko/scrapy/defaults.py
vanko/scrapy/downloader.py
vanko/scrapy/fast_exit.py
vanko/scrapy/helpers.py
vanko/scrapy/httpcache.py
vanko/scrapy/item_loader.py
vanko/scrapy/pipelines.py
vanko/scrapy/reqser.py
vanko/scrapy/restart_on.py
vanko/scrapy/scheduler.py
vanko/scrapy/settings.py
vanko/scrapy/sftp_httpcache.py
vanko/scrapy/sftp_store.py
vanko/scrapy/show_ip.py
vanko/scrapy/spider.py
vanko/scrapy/spider_loader.py
vanko/scrapy/stats.py
vanko/scrapy/useragent.py
vanko/scrapy/useragent.xml
vanko/scrapy/mongo/__init__.py
vanko/scrapy/mongo/connection.py
vanko/scrapy/mongo/dupefilter.py
vanko/scrapy/mongo/httpcache.py
vanko/scrapy/mongo/queue.py
vanko/scrapy/mongo/stats.py
vanko/scrapy/qt4/__init__.py
vanko/scrapy/qt4/defs.py
vanko/scrapy/qt4/filter.py
vanko/scrapy/qt4/handlers.py
vanko/scrapy/qt4/login.py
vanko/scrapy/qt4/qt4webkit.py
vanko/scrapy/qt4/test.py
vanko/scrapy/qt4/utils.py
vanko/scrapy/redis/__init__.py
vanko/scrapy/redis/connection.py
vanko/scrapy/redis/dupefilter.py
vanko/scrapy/redis/httpcache.py
vanko/scrapy/redis/pipelines.py
vanko/scrapy/redis/queue.py
vanko/scrapy/redis/spiders.py
vanko/scrapy/redis/stats.py
vanko/scrapy/redis/tests.py
vanko/scrapy/webdriver/__init__.py
vanko/scrapy/webdriver/action_chains.py
vanko/scrapy/webdriver/download.py
vanko/scrapy/webdriver/http.py
vanko/scrapy/webdriver/manager.py
vanko/scrapy/webdriver/middlewares.py
vanko/scrapy/webdriver/response.py
vanko/scrapy/webdriver/selector.py
vanko/scrapy/webdriver/spider.py
