Metadata-Version: 2.0
Name: hero-crawl
Version: 0.1.4
Summary: Helpers for Scrapy and Flask on Heroku
Home-page: https://github.com/ivandeex/hero-crawl
Author: Ivan Andreev
Author-email: ivandeex@gmail.com
License: MIT
Platform: UNKNOWN
Classifier: Development Status :: 3 - Alpha
Classifier: Intended Audience :: Developers
Classifier: Operating System :: OS Independent
Classifier: Programming Language :: Python :: 2.7
Classifier: Framework :: Scrapy
Classifier: Topic :: Utilities
Classifier: License :: OSI Approved :: BSD License
